superccm/__init__.py
superccm/default.py
superccm/api/__init__.py
superccm/api/api.py
superccm/core/__init__.py
superccm/core/module.py
superccm/core/workflow.py
superccm/impl/__init__.py
superccm/impl/common.py
superccm/impl/modules.py
superccm/impl/graph/__init__.py
superccm/impl/graph/graphify.py
superccm/impl/graph/vis.py
superccm/impl/io/__init__.py
superccm/impl/io/read.py
superccm/impl/metircs/__init__.py
superccm/impl/metircs/bfs.py
superccm/impl/metircs/extract_trunk.py
superccm/impl/metircs/fracdim.py
superccm/impl/metircs/metrics.py
superccm/impl/metircs/reconstruction_binary.py
superccm/impl/metircs/tc.py
superccm/impl/metircs/utils.py
superccm/impl/segment/__init__.py
superccm/impl/segment/ccm.onnx
superccm/impl/segment/segment.py
superccm/impl/skeleton/__init__.py
superccm/impl/skeleton/skeletonize.py
superccm/impl/trunk/__init__.py
superccm/impl/trunk/ep_path.py
superccm/impl/trunk/eval_path.py
superccm/impl/trunk/extract_trunks.py
superccm/impl/utils/__init__.py
superccm/impl/utils/ccm_vignetting.py
superccm/impl/utils/curvature.py
superccm/impl/utils/estimate_width.py
superccm/impl/utils/histogram_matching.py
superccm/impl/utils/prune.py
superccm/impl/utils/ref.png
superccm/impl/utils/tools.py
superccm-1.0.1.dist-info/licenses/LICENSE
superccm-1.0.1.dist-info/METADATA
superccm-1.0.1.dist-info/WHEEL
superccm-1.0.1.dist-info/top_level.txt
superccm-1.0.1.dist-info/RECORD
