Metadata-Version: 2.4
Name: superccm
Version: 1.0.1
Summary: An Open-Source Python Toolkit for Automated Quantification of Corneal Nerve Fibers in Confocal Microscopy Images
Home-page: https://https://github.com/SummerColdWind
Author: Qincheng Qiao
Author-email: jugking6688@gmail.com
Classifier: Development Status :: 1 - Planning
Classifier: License :: OSI Approved :: GNU General Public License v3 (GPLv3)
Classifier: Topic :: Scientific/Engineering :: Medical Science Apps.
Requires-Python: >=3.10
License-File: LICENSE
Requires-Dist: aiccm
Requires-Dist: matplotlib==3.7.0
Requires-Dist: numpy<2.0.0
Requires-Dist: scikit-learn==1.7.0
Requires-Dist: pywebview
Requires-Dist: pyinstaller
Dynamic: author
Dynamic: author-email
Dynamic: classifier
Dynamic: description
Dynamic: description-content-type
Dynamic: home-page
Dynamic: license-file
Dynamic: requires-dist
Dynamic: requires-python
Dynamic: summary
